lazybrains/__init__.py
lazybrains/core.py
lazybrains-4.0.1.dist-info/METADATA
lazybrains-4.0.1.dist-info/WHEEL
lazybrains-4.0.1.dist-info/top_level.txt
lazybrains-4.0.1.dist-info/RECORD
